[{
	"name": "首页",
	"icon": "home",
	"path": "/home"
}, {
	"name": "社团组织",
	"icon": "team",
	"children": [{
		"name": "社团管理",
		"icon": "solution",
		"path": "/community"
	}, {
		"name": "人员组织管理",
		"icon": "team"
	}]
}, {
	"name": "公告相关",
	"icon": "sound",
	"children": [{
		"name": "新增公告",
		"icon": "form",
		"path": "/newBulletin"
	}, {
		"name": "公告管理",
		"icon": "snippets"
	}, {
		"name": "流量统计",
		"icon": "area-chart"
	}]
}, {
	"name": "管理员管理",
	"icon": "lock"
}, {
	"name": "个人信息",
	"icon": "user",
	"path": "/user"
}]